pretix_dbevent/__init__.py
pretix_dbevent/apps.py
pretix_dbevent/forms.py
pretix_dbevent/helpers.py
pretix_dbevent/models.py
pretix_dbevent/signals.py
pretix_dbevent/urls.py
pretix_dbevent/views.py
pretix_dbevent/locale/django.pot
pretix_dbevent/locale/de/LC_MESSAGES/django.mo
pretix_dbevent/locale/de/LC_MESSAGES/django.po
pretix_dbevent/locale/de_Informal/.gitkeep
pretix_dbevent/locale/de_Informal/LC_MESSAGES/django.mo
pretix_dbevent/locale/de_Informal/LC_MESSAGES/django.po
pretix_dbevent/migrations/0001_initial.py
pretix_dbevent/migrations/0002_rename_issue_coupons_itemdbeventconfig_show_offer.py
pretix_dbevent/migrations/__init__.py
pretix_dbevent/static/pretix_dbevent/.gitkeep
pretix_dbevent/static/pretix_dbevent/db-logo.svg
pretix_dbevent/static/pretix_dbevent/pretix-dbevent.scss
pretix_dbevent/templates/pretix_dbevent/.gitkeep
pretix_dbevent/templates/pretix_dbevent/order_position_info.html
pretix_dbevent/templates/pretix_dbevent/presale_head.html
pretix_dbevent/templates/pretix_dbevent/settings.html
pretix_dbevent-1.0.0.dist-info/licenses/LICENSE
pretix_dbevent-1.0.0.dist-info/METADATA
pretix_dbevent-1.0.0.dist-info/WHEEL
pretix_dbevent-1.0.0.dist-info/entry_points.txt
pretix_dbevent-1.0.0.dist-info/top_level.txt
pretix_dbevent-1.0.0.dist-info/RECORD
