Metadata-Version: 2.4
Name: pretix-dbevent
Version: 1.0.0
Summary: Advertise the DB Event Offers for discounted and sustainable train travel to your attendees
Author-email: pretix team <support@pretix.eu>
Maintainer-email: pretix team <support@pretix.eu>
License: Apache
Project-URL: homepage, https://github.com/pretix/pretix-dbevent/
Project-URL: repository, https://github.com/pretix/pretix-dbevent/
Keywords: pretix
License-File: LICENSE
Dynamic: license-file
